MANIFEST.in
README.txt
setup.cfg
setup.py
atreal/__init__.py
atreal.filecart.egg-info/PKG-INFO
atreal.filecart.egg-info/SOURCES.txt
atreal.filecart.egg-info/dependency_links.txt
atreal.filecart.egg-info/entry_points.txt
atreal.filecart.egg-info/namespace_packages.txt
atreal.filecart.egg-info/not-zip-safe
atreal.filecart.egg-info/requires.txt
atreal.filecart.egg-info/top_level.txt
atreal/filecart/__init__.py
atreal/filecart/cart.py
atreal/filecart/comments.py
atreal/filecart/configure.zcml
atreal/filecart/content.py
atreal/filecart/events.py
atreal/filecart/interfaces.py
atreal/filecart/marker.py
atreal/filecart/browser/__init__.py
atreal/filecart/browser/arrow_bottom_right.png
atreal/filecart/browser/batching.pt
atreal/filecart/browser/comments.pt
atreal/filecart/browser/configure.zcml
atreal/filecart/browser/controlpanel.pt
atreal/filecart/browser/controlpanel.py
atreal/filecart/browser/controls.pt
atreal/filecart/browser/fc-controls-actions_mapping.png
atreal/filecart/browser/filecart.pt
atreal/filecart/browser/filecart.py
atreal/filecart/browser/filecart_icon.png
atreal/filecart/browser/filecartzip.py
atreal/filecart/browser/table.pt
atreal/filecart/browser/tableview.py
atreal/filecart/browser/viewlets.css
atreal/filecart/browser/viewlets.kss
atreal/filecart/browser/viewlets.py
atreal/filecart/browser/views.py
atreal/filecart/locales/atreal.filecart.pot
atreal/filecart/locales/fr/LC_MESSAGES/atreal.filecart.mo
atreal/filecart/locales/fr/LC_MESSAGES/atreal.filecart.po
atreal/filecart/portlets/__init__.py
atreal/filecart/portlets/cartportlet.pt
atreal/filecart/portlets/cartportlet.py
atreal/filecart/portlets/configure.zcml
atreal/filecart/profiles/default/actionicons.xml
atreal/filecart/profiles/default/actions.xml
atreal/filecart/profiles/default/browserlayer.xml
atreal/filecart/profiles/default/componentregistry.xml
atreal/filecart/profiles/default/controlpanel.xml
atreal/filecart/profiles/default/cssregistry.xml
atreal/filecart/profiles/default/kssregistry.xml
atreal/filecart/profiles/default/metadata.xml
atreal/filecart/profiles/default/portlets.xml
atreal/filecart/profiles/default/rolemap.xml
docs/HISTORY.txt
docs/INSTALL.txt
docs/LICENSE.GPL
docs/LICENSE.txt