Metadata-Version: 1.1
Name: atreal.filecart
Version: 1.1.0
Summary: A cart for Plone to add file and download them in an archive.
Home-page: http://www.atreal.net/
Author: atReal
Author-email: contact@atreal.net
License: GPL
Platform: UNKNOWN
Classifier: Framework :: Plone
Classifier: Programming Language :: Python
Classifier: Topic :: Software Development :: Libraries :: Python Modules
